htmlfactory/InnerHtml.py
htmlfactory/SingletonTag.py
htmlfactory/TagAndClassStr.py
htmlfactory/TagAttribute.py
htmlfactory/TagAttributeList.py
htmlfactory/TagFactory.py
htmlfactory/__init__.py
htmlfactory-0.0.1.dist-info/LICENSE
htmlfactory-0.0.1.dist-info/METADATA
htmlfactory-0.0.1.dist-info/WHEEL
htmlfactory-0.0.1.dist-info/top_level.txt
htmlfactory-0.0.1.dist-info/RECORD
