Metadata-Version: 2.1
Name: htmlfactory
Version: 0.0.1
Summary: A simple way to produce HTML with Python.
Home-page: https://github.com/jgrugru/htmlfactory
Author: Jeff Gruenbaum
Author-email: jeff.gruenbaum@gmail.com
License: MIT
Keywords: html,template,templating,xml,document,form,rendering
Platform: UNKNOWN
Classifier: License :: OSI Approved :: MIT License
Classifier: Programming Language :: Python :: 3
Classifier: Programming Language :: Python :: 3.7
Requires-Dist: beautifulsoup4 (>=2.2)
